LICENSE
MANIFEST.in
README.md
setup.py
x509sak/ASN1Models.py
x509sak/ASN1Wrapper.py
x509sak/AdvancedColorPalette.py
x509sak/AlgorithmDB.py
x509sak/AnalysisPrinter.py
x509sak/BaseAction.py
x509sak/BijectiveDict.py
x509sak/CAManager.py
x509sak/CertificateAnalyzer.py
x509sak/CertificatePool.py
x509sak/CertificateRevocationList.py
x509sak/CmdLineArgs.py
x509sak/ConsolePrinter.py
x509sak/CurveDB.py
x509sak/DSAParameters.py
x509sak/DistinguishedName.py
x509sak/ECCMath.py
x509sak/ECPrivateKey.py
x509sak/EDPrivateKey.py
x509sak/Exceptions.py
x509sak/FileWriter.py
x509sak/FlagChecker.py
x509sak/FriendlyArgumentParser.py
x509sak/HexDump.py
x509sak/IPAddress.py
x509sak/Intervals.py
x509sak/KeySpecification.py
x509sak/KwargsChecker.py
x509sak/ModulusDB.py
x509sak/MultiCommand.py
x509sak/NumberTheory.py
x509sak/OID.py
x509sak/OpenSSLCAIndexFile.py
x509sak/OpenSSLConfig.py
x509sak/OpenSSLTools.py
x509sak/OtherModels.py
x509sak/PEMDERObject.py
x509sak/PRNG.py
x509sak/ParallelExecutor.py
x509sak/PassphraseGenerator.py
x509sak/PrefixMatcher.py
x509sak/PrimeDB.py
x509sak/PrivateKeyStorage.py
x509sak/PublicKey.py
x509sak/RSAPSSParameters.py
x509sak/RSAPrivateKey.py
x509sak/ScrapeEngine.py
x509sak/StringParser.py
x509sak/SubprocessExecutor.py
x509sak/TempUMask.py
x509sak/Tools.py
x509sak/WorkDir.py
x509sak/X509Certificate.py
x509sak/X509Extensions.py
x509sak/__init__.py
x509sak/__main__.py
x509sak.egg-info/PKG-INFO
x509sak.egg-info/SOURCES.txt
x509sak.egg-info/dependency_links.txt
x509sak.egg-info/entry_points.txt
x509sak.egg-info/requires.txt
x509sak.egg-info/top_level.txt
x509sak/actions/ActionBuildChain.py
x509sak/actions/ActionCreateCA.py
x509sak/actions/ActionCreateCRL.py
x509sak/actions/ActionCreateCSR.py
x509sak/actions/ActionDebug.py
x509sak/actions/ActionDumpKey.py
x509sak/actions/ActionExamineCert.py
x509sak/actions/ActionFindCert.py
x509sak/actions/ActionForgeCert.py
x509sak/actions/ActionGenerateBrokenDSA.py
x509sak/actions/ActionGenerateBrokenRSA.py
x509sak/actions/ActionGraphPool.py
x509sak/actions/ActionHashPart.py
x509sak/actions/ActionJudgementCode.py
x509sak/actions/ActionRevokeCRT.py
x509sak/actions/ActionScrape.py
x509sak/actions/ActionSignCSR.py
