Metadata-Version: 2.1
Name: x509sak
Version: 0.0.4
Summary: X.509 Swiss Army Knife is a toolkit atop OpenSSL to ease generation of CAs and aid white-hat pentesting
Home-page: https://github.com/johndoe31415/x509sak
Author: Johannes Bauer
Author-email: joe@johannes-bauer.com
License: gpl-3.0
Download-URL: https://github.com/johndoe31415/x509sak/archive/v0.0.4.tar.gz
Keywords: x509,certificate,toolkit,openssl,pki,pentesting,pkcs11,ca
Platform: UNKNOWN
Classifier: Development Status :: 5 - Production/Stable
Classifier: Intended Audience :: Developers
Classifier: License :: OSI Approved :: GNU General Public License v3 (GPLv3)
Classifier: Programming Language :: Python :: 3
Classifier: Programming Language :: Python :: 3 :: Only
Classifier: Programming Language :: Python :: 3.5
Classifier: Programming Language :: Python :: 3.6
Classifier: Programming Language :: Python :: 3.7
Classifier: Programming Language :: Python :: 3.8
Classifier: Programming Language :: Python :: 3.9
Classifier: Programming Language :: Python :: 3.10
License-File: LICENSE
